micropython_bma220/__init__.py
micropython_bma220/bma220.py
micropython_bma220/bma220_const.py
micropython_bma220/bma220_lowg_detection.py
micropython_bma220/bma220_orientation.py
micropython_bma220/bma220_slope.py
micropython_bma220/bma220_tap_sensing.py
micropython_bma220/i2c_helpers.py
micropython_bma220-0.1.2.dist-info/LICENSE
micropython_bma220-0.1.2.dist-info/METADATA
micropython_bma220-0.1.2.dist-info/WHEEL
micropython_bma220-0.1.2.dist-info/top_level.txt
micropython_bma220-0.1.2.dist-info/RECORD
