Metadata-Version: 2.1
Name: micropython-bma220
Version: 0.1.2
Summary: MicroPython Driver for the Bosch BMA220 Accelerometer
Author-email: JDM <xxyx@mailmeto.mozmail.com>
License: MIT
Project-URL: Homepage, https://github.com/jposada202020/MicroPython_BMA220
Keywords: sensor,micropython,bma220,acceleration,driver,bosch,accelerometer,gravity,slope,tap,orientation
Classifier: Intended Audience :: Developers
Classifier: Topic :: Software Development :: Libraries
Classifier: Topic :: Software Development :: Embedded Systems
Classifier: Topic :: System :: Hardware
Classifier: License :: OSI Approved :: MIT License
Classifier: Programming Language :: Python :: Implementation :: MicroPython
License-File: LICENSE
